[
  {
    "store": "037",
    "failed_criteria": [
      "A cable crosses a shared footpath/walkway creating a trip hazard"
    ],
    "action_plan": [
      "Re-route the cable along furniture edges or behind the desk so it does not cross any shared walkway"
    ],
    "visual_feedback": [
      "Cable from the computer is visible crossing the open aisle under the desk, posing a trip hazard"
    ],
    "notes": ""
  },
  {
    "store": "064",
    "failed_criteria": [
      "All visible cables are routed along furniture edges, walls, or tucked away from walkways.",
      "No cables should dangle in a way that could cause a trip hazard or obstruct access to equipment."
    ],
    "action_plan": [
      "Re-route cables to run along furniture edges or walls, securing them with clips or ties so they do not cross the shared walkway.",
      "Bundle or clip loose cable segments under the desk to eliminate any dangling sections that extend into the open aisle."
    ],
    "visual_feedback": [
      "Cable from the rightmost desk is running across the main walkway, creating a trip hazard.",
      "Loose cable segment under the right desk dangles into the shared footpath."
    ],
    "notes": ""
  },
  {
    "store": "089",
    "failed_criteria": [
      "All visible cables are routed along furniture edges, walls, or tucked away from walkways.",
      "No cables should dangle in a way that could cause a trip hazard or obstruct access to equipment."
    ],
    "action_plan": [
      "Re-route cables to run along desk edges or walls, away from open pathways.",
      "Use cable clips, conduit, or cable covers to secure any cables crossing shared walkways and eliminate trip hazards."
    ],
    "visual_feedback": [
      "In the second submission image, a loose cable extends across the front opening of the desk into the walkway, posing a trip hazard."
    ],
    "notes": ""
  }
]